rdatools/__init__.py
rdatools/base/__init__.py
rdatools/base/approxequal.py
rdatools/base/constants.py
rdatools/base/energy.py
rdatools/base/geoutils.py
rdatools/base/graph.py
rdatools/base/load.py
rdatools/base/misc.py
rdatools/base/population.py
rdatools/base/readwrite.py
rdatools/base/requireargs.py
rdatools/base/timers.py
rdatools/base/union_find.py
rdatools/dccvt/__init__.py
rdatools/dccvt/balzer.py
rdatools/dccvt/balzerio.py
rdatools/dccvt/helpers.py
rdatools/ei/__init__.py
rdatools/ei/analyze.py
rdatools/ei/minority.py
rdatools/ensemble/__init__.py
rdatools/ensemble/ensemble_io.py
rdatools/ensemble/frcw.py
rdatools/ensemble/graph.py
rdatools/ensemble/metautils.py
rdatools/ensemble/notable_maps.py
rdatools/ensemble/prep_data.py
rdatools/ensemble/random_map.py
rdatools/ensemble/rmfrsp.py
rdatools/ensemble/rmfrst.py
rdatools/ensemble/score.py
rdatools/ensemble/ust.py
rdatools/ensemble/utils.py
rdatools/rootmap/__init__.py
rdatools/rootmap/compact.py
rdatools/score/__init__.py
rdatools/score/analyze.py
rdatools/score/discrete_compactness.py
rdatools/score/smallestenclosingcircle.py
rda_toolkit-0.0.4.dist-info/LICENSE
rda_toolkit-0.0.4.dist-info/METADATA
rda_toolkit-0.0.4.dist-info/WHEEL
rda_toolkit-0.0.4.dist-info/top_level.txt
rda_toolkit-0.0.4.dist-info/RECORD
